autoball/__init__.py
autoball-1.0.0.dist-info/LICENSE
autoball-1.0.0.dist-info/METADATA
autoball-1.0.0.dist-info/WHEEL
autoball-1.0.0.dist-info/top_level.txt
autoball-1.0.0.dist-info/RECORD
