Metadata-Version: 2.1
Name: autoball
Version: 1.0.0
Summary: This module simply just automatically generates random 8ball choices.
Home-page: https://github.com/ItzBlueBerries/Autoball
Author: Fruitsy
License: UNKNOWN
Platform: UNKNOWN
Classifier: Programming Language :: Python :: 3
Classifier: License :: OSI Approved :: MIT License
Classifier: Operating System :: OS Independent
Requires-Python: >=3.8.2
